kitchenowl_python/__init__.py
kitchenowl_python/const.py
kitchenowl_python/exceptions.py
kitchenowl_python/kitchenowl.py
kitchenowl_python/types.py
kitchenowl_python-0.0.1.dist-info/LICENSE
kitchenowl_python-0.0.1.dist-info/METADATA
kitchenowl_python-0.0.1.dist-info/WHEEL
kitchenowl_python-0.0.1.dist-info/top_level.txt
kitchenowl_python-0.0.1.dist-info/RECORD
