Metadata-Version: 2.1
Name: kitchenowl-python
Version: 0.0.1
Summary: A python wrapper for the KitchenOwl API
Author: super-qua
Author-email: Tom Bursch <tom@kitchenowl.org>
License: MIT License
Project-URL: Homepage, https://kitchenowl.org
Project-URL: Repository, https://github.com/tombursch/kitchenowl-python
Project-URL: Issues, https://github.com/TomBursch/kitchenowl/issues
Project-URL: Changelog, https://github.com/tombursch/kitchenowl-python/blob/main/CHANGELOG.md
Keywords: kitchenowl
Classifier: Development Status :: 3 - Alpha
Classifier: Programming Language :: Python
Requires-Python: >=3.8
License-File: LICENSE
Requires-Dist: aiohttp==3.10.5
Provides-Extra: test
Requires-Dist: aioresponses==0.7.6; extra == "test"
Requires-Dist: pytest==8.2.2; extra == "test"
Requires-Dist: pytest-asyncio==0.23.7; extra == "test"
Requires-Dist: pytest-cov==6.0.0; extra == "test"
Requires-Dist: syrupy==4.6.1; extra == "test"
Provides-Extra: lint
Requires-Dist: ruff==0.6.1; extra == "lint"
